[
  [
    {
      "Fixed_original_average": 23.88491303482275,
      "Fixed_original_median": 2.5806843042373657,
      "Fixed_original_75th_percentile": 8.637558201948801,
      "Fixed_original_95th_percentile": 122.35824464559525
    },
    {
      "Fixed_rewritten_average": 9.97080989700738,
      "Fixed_rewritten_median": 1.2245723803838093,
      "Fixed_rewritten_75th_percentile": 6.8648176675,
      "Fixed_rewritten_95th_percentile": 26.97250658273696
    }
  ],
  {
    "id": 2,
    "equivalence": true,
    "original_query": "SELECT \"t\".\"EXPR0\", 2 + 3 AS \"f1\", MAX(\"t\".\"FIVE\") FROM \"EMP\", (VALUES (4, 5)) AS \"t\" (\"EXPR0\", \"FIVE\") GROUP BY \"t\".\"EXPR0\", 2 + 3",
    "rewritten_query": "SELECT 4 AS \"EXPR0\", 5 AS \"f1\", 5 AS \"MAX\"",
    "original_execution_time": 1.3798015117645264,
    "rewrite_execution_time": 0.00010275840759277344,
    "speed_up": 0.9999255266741509,
    "times_up": 13427.62645011601
  },
  {
    "id": 3,
    "equivalence": true,
    "original_query": "SELECT \"NAME\" FROM \"DEPT\" WHERE EXISTS (SELECT 1 FROM (SELECT 2 * \"DEPTNO\" AS \"f0\" FROM \"DEPT\" GROUP BY 2 * \"DEPTNO\") AS \"t0\" WHERE \"DEPT\".\"DEPTNO\" = \"t0\".\"f0\")",
    "rewritten_query": "/*+ NoHashJoin(DEPT DEPT_1) Rows(DEPT t0 #1000) */\nSELECT \"NAME\" FROM \"DEPT\" WHERE EXISTS (SELECT 1 FROM (SELECT 2 * \"DEPTNO\" AS \"f0\" FROM \"DEPT\" GROUP BY 2 * \"DEPTNO\") AS \"t0\" WHERE \"DEPT\".\"DEPTNO\" = \"t0\".\"f0\")",
    "original_execution_time": 0.5460665225982666,
    "rewrite_execution_time": 0.48082693417867023,
    "speed_up": 0.11947186967107341,
    "times_up": 1.135682058932568
  },
  {
    "id": 4,
    "equivalence": true,
    "original_query": "SELECT \"EMP\".\"SAL\" + \"BONUS\".\"COMM\", SUM(\"BONUS\".\"SAL\" + \"BONUS\".\"SAL\" + 100) OVER (PARTITION BY \"BONUS\".\"JOB\" RANGE BETWEEN UNBOUNDED PRECEDING AND UNBOUNDED FOLLOWING) FROM \"EMP\" INNER JOIN \"BONUS\" ON \"EMP\".\"ENAME\" = \"BONUS\".\"ENAME\" AND \"EMP\".\"DEPTNO\" = 10",
    "rewritten_query": "SELECT \"EMP\".\"SAL\" + \"BONUS\".\"COMM\",\n  SUM(2 * \"BONUS\".\"SAL\" + 100) OVER (PARTITION BY \"BONUS\".\"JOB\" ROWS BETWEEN UNBOUNDED PRECEDING AND UNBOUNDED FOLLOWING) \nFROM \"EMP\" \nINNER JOIN \"BONUS\" \n  ON \"EMP\".\"ENAME\" = \"BONUS\".\"ENAME\" \nWHERE \"EMP\".\"DEPTNO\" = 10;",
    "original_execution_time": 7.3580671946207685,
    "rewrite_execution_time": 8.279128074645996,
    "speed_up": -0.1251770139716288,
    "times_up": 0.8887490480010951
  },
  {
    "id": 5,
    "equivalence": true,
    "original_query": "SELECT \"NAME\" FROM (SELECT \"DEPTNO\", \"NAME\" FROM \"DEPT\" WHERE EXISTS (SELECT 1 FROM (SELECT 2 * \"DEPTNO\" AS \"f0\" FROM \"DEPT\" GROUP BY 2 * \"DEPTNO\") AS \"t5\" WHERE \"DEPTNO\" = \"t5\".\"f0\")) AS \"t2\"",
    "rewritten_query": "SELECT \"NAME\" FROM (SELECT \"DEPTNO\", \"NAME\" FROM \"DEPT\" WHERE EXISTS (SELECT 1 FROM (SELECT 2 * \"DEPTNO\" AS \"f0\" FROM \"DEPT\" GROUP BY 2 * \"DEPTNO\") AS \"t5\" WHERE \"DEPTNO\" = \"t5\".\"f0\")) AS \"t2\"",
    "original_execution_time": 0.5264325936635336,
    "rewrite_execution_time": 0.5244934558868408,
    "speed_up": 0.003683544294242796,
    "times_up": 1.0036971629577607
  },
  {
    "id": 6,
    "equivalence": true,
    "original_query": "SELECT * FROM (SELECT UPPER(SUBSTRING(\"X\" FROM 1 FOR 2) || SUBSTRING(\"X\" FROM 3)) AS \"U\", SUBSTRING(\"X\" FROM 1 FOR 1) AS \"S\" FROM (SELECT * FROM (SELECT 'table' AS \"X\" FROM (VALUES (TRUE)) AS \"t\" (\"EXPR0\") UNION SELECT 'view' AS \"EXPR0\" FROM (VALUES (TRUE)) AS \"t\" (\"EXPR0\")) AS \"t\" UNION SELECT 'foreign table' AS \"EXPR0\" FROM (VALUES (TRUE)) AS \"t\" (\"EXPR0\")) AS \"t6\") AS \"t7\" WHERE \"U\" = 'TABLE'",
    "rewritten_query": "SELECT 'TABLE' AS \"U\", 't' AS \"S\"",
    "original_execution_time": 0.00028832753499348957,
    "rewrite_execution_time": 9.497006734212239e-05,
    "speed_up": 0.6706174200661522,
    "times_up": 3.035983263598326
  },
  {
    "id": 7,
    "equivalence": true,
    "original_query": "SELECT \"t6\".\"ENAME\" FROM (SELECT \"JOB\" FROM \"EMP\" WHERE \"ENAME\" = 'A' GROUP BY \"JOB\") AS \"t5\" LEFT JOIN (SELECT \"ENAME\", \"JOB\" FROM \"EMP\" GROUP BY \"ENAME\", \"JOB\") AS \"t6\" ON \"t5\".\"JOB\" = \"t6\".\"JOB\" GROUP BY \"t6\".\"ENAME\"",
    "rewritten_query": "SELECT DISTINCT \"ENAME\"  \nFROM \"EMP\"  \nWHERE \"JOB\" IN (SELECT DISTINCT \"JOB\" FROM \"EMP\" WHERE \"ENAME\" = 'A');",
    "original_execution_time": 56.26316920916239,
    "rewrite_execution_time": 5.037307182947795,
    "speed_up": 0.9104688332749042,
    "times_up": 11.169294856510538
  },
  {
    "id": 8,
    "equivalence": true,
    "original_query": "SELECT \"t2\".\"EMPNO\", \"t2\".\"ENAME\", \"t2\".\"JOB\", \"t2\".\"MGR\", \"t2\".\"HIREDATE\", \"t2\".\"SAL\", \"t2\".\"COMM\", \"t2\".\"DEPTNO\", \"t2\".\"SLACKER\", \"t3\".\"DEPTNO\" AS \"DEPTNO0\", \"t3\".\"NAME\" FROM (SELECT \"EMPNO\", \"ENAME\", \"JOB\", \"MGR\", \"HIREDATE\", \"SAL\", \"COMM\", \"DEPTNO\", \"SLACKER\" FROM \"EMP\" ORDER BY \"SAL\") AS \"t2\" INNER JOIN (SELECT * FROM \"DEPT\") AS \"t3\" ON \"t2\".\"DEPTNO\" = \"t3\".\"DEPTNO\" ORDER BY \"t2\".\"SAL\" FETCH NEXT 10 ROWS ONLY",
    "rewritten_query": "/*+ HashJoin(t2 t3) NoNestLoop(t2 t3) */\nSELECT \"t2\".\"EMPNO\", \"t2\".\"ENAME\", \"t2\".\"JOB\", \"t2\".\"MGR\", \"t2\".\"HIREDATE\", \"t2\".\"SAL\", \"t2\".\"COMM\", \"t2\".\"DEPTNO\", \"t2\".\"SLACKER\", \"t3\".\"DEPTNO\" AS \"DEPTNO0\", \"t3\".\"NAME\" FROM (SELECT \"EMPNO\", \"ENAME\", \"JOB\", \"MGR\", \"HIREDATE\", \"SAL\", \"COMM\", \"DEPTNO\", \"SLACKER\" FROM \"EMP\" ORDER BY \"SAL\") AS \"t2\" INNER JOIN (SELECT * FROM \"DEPT\") AS \"t3\" ON \"t2\".\"DEPTNO\" = \"t3\".\"DEPTNO\" ORDER BY \"t2\".\"SAL\" FETCH NEXT 10 ROWS ONLY",
    "original_execution_time": 11.770477374394735,
    "rewrite_execution_time": 11.06512986,
    "speed_up": 0.05992514083830904,
    "times_up": 1.0637450733356992
  },
  {
    "id": 9,
    "equivalence": true,
    "original_query": "SELECT * FROM (SELECT * FROM \"EMP\" WHERE \"DEPTNO\" = \"EMPNO\") AS \"t1\" INNER JOIN \"DEPT\" AS \"DEPT0\" ON \"t1\".\"DEPTNO\" = \"DEPT0\".\"DEPTNO\"",
    "rewritten_query": "SELECT \"EMP\".*, \"DEPT0\".*\nFROM \"EMP\"\nINNER JOIN \"DEPT\" AS \"DEPT0\" ON \"EMP\".\"DEPTNO\" = \"DEPT0\".\"DEPTNO\"\nWHERE \"EMP\".\"DEPTNO\" = \"EMP\".\"EMPNO\";",
    "original_execution_time": 0.9265867869059244,
    "rewrite_execution_time": 1.0531006654103596,
    "speed_up": -0.13653753786722195,
    "times_up": 0.8798653512813642
  },
  {
    "id": 10,
    "equivalence": true,
    "original_query": "SELECT \"t2\".\"EMPNO\", \"t2\".\"ENAME\", \"t2\".\"JOB\", \"t2\".\"MGR\", \"t2\".\"HIREDATE\", \"t2\".\"SAL\", \"t2\".\"COMM\", \"t2\".\"DEPTNO\", \"t2\".\"SLACKER\", \"t3\".\"DEPTNO\" AS \"DEPTNO0\", \"t3\".\"NAME\" FROM (SELECT \"EMPNO\", \"ENAME\", \"JOB\", \"MGR\", \"HIREDATE\", \"SAL\", \"COMM\", \"DEPTNO\", \"SLACKER\" FROM \"EMP\" ORDER BY \"SAL\" FETCH NEXT 10 ROWS ONLY) AS \"t2\" LEFT JOIN (SELECT * FROM \"DEPT\") AS \"t3\" ON \"t2\".\"DEPTNO\" = \"t3\".\"DEPTNO\" ORDER BY \"t2\".\"SAL\" FETCH NEXT 10 ROWS ONLY",
    "rewritten_query": "/*+ Rows(EMP #100) */\nSELECT \"t2\".\"EMPNO\", \"t2\".\"ENAME\", \"t2\".\"JOB\", \"t2\".\"MGR\", \"t2\".\"HIREDATE\", \"t2\".\"SAL\", \"t2\".\"COMM\", \"t2\".\"DEPTNO\", \"t2\".\"SLACKER\", \"t3\".\"DEPTNO\" AS \"DEPTNO0\", \"t3\".\"NAME\" FROM (SELECT \"EMPNO\", \"ENAME\", \"JOB\", \"MGR\", \"HIREDATE\", \"SAL\", \"COMM\", \"DEPTNO\", \"SLACKER\" FROM \"EMP\" ORDER BY \"SAL\" FETCH NEXT 10 ROWS ONLY) AS \"t2\" LEFT JOIN (SELECT * FROM \"DEPT\") AS \"t3\" ON \"t2\".\"DEPTNO\" = \"t3\".\"DEPTNO\" ORDER BY \"t2\".\"SAL\" FETCH NEXT 10 ROWS ONLY",
    "original_execution_time": 3.6602250734965005,
    "rewrite_execution_time": 3.63436369,
    "speed_up": 0.007065517277547117,
    "times_up": 1.0071157940433035
  },
  {
    "id": 11,
    "equivalence": true,
    "original_query": "SELECT SUM(100) OVER (PARTITION BY \"DEPTNO\", \"SAL\" ORDER BY \"SAL\" RANGE BETWEEN UNBOUNDED PRECEDING AND CURRENT ROW) AS \"COL1\", SUM(100) OVER (PARTITION BY \"SAL\" ORDER BY \"DEPTNO\" RANGE BETWEEN UNBOUNDED PRECEDING AND CURRENT ROW) AS \"COL2\", SUM(\"SAL\") OVER (PARTITION BY \"DEPTNO\" ORDER BY \"SAL\" RANGE BETWEEN UNBOUNDED PRECEDING AND CURRENT ROW) AS \"COL3\" FROM \"EMP\" WHERE \"SAL\" = 5000",
    "rewritten_query": "SELECT SUM(100) OVER (PARTITION BY \"DEPTNO\", \"SAL\" ORDER BY \"SAL\" RANGE BETWEEN UNBOUNDED PRECEDING AND CURRENT ROW) AS \"COL1\", SUM(100) OVER (PARTITION BY \"SAL\" ORDER BY \"DEPTNO\" RANGE BETWEEN UNBOUNDED PRECEDING AND CURRENT ROW) AS \"COL2\", SUM(\"SAL\") OVER (PARTITION BY \"DEPTNO\" ORDER BY \"SAL\" RANGE BETWEEN UNBOUNDED PRECEDING AND CURRENT ROW) AS \"COL3\" FROM \"EMP\" WHERE \"SAL\" = 5000",
    "original_execution_time": 1.2466312249501545,
    "rewrite_execution_time": 1.3457043965657551,
    "speed_up": -0.07947271785973589,
    "times_up": 0.9263782061881971
  },
  {
    "id": 12,
    "equivalence": false,
    "original_query": "SELECT \"t0\".\"JOB\" FROM (SELECT \"EMPNO\", \"ENAME\", \"JOB\", \"MGR\", \"HIREDATE\", \"SAL\", \"COMM\", \"DEPTNO\", \"SLACKER\", \"DEPTNO\" + \"EMPNO\" AS \"f9\" FROM \"EMP\" WHERE \"ENAME\" = 'A') AS \"t0\" FULL JOIN (SELECT \"DEPTNO\", \"NAME\", \"DEPTNO\" + 5 AS \"f2\" FROM \"DEPT\") AS \"t1\" ON \"t0\".\"JOB\" = \"t1\".\"NAME\" AND \"t0\".\"f9\" = \"t1\".\"f2\" GROUP BY \"t0\".\"JOB\"",
    "rewritten_query": "SELECT \"EMP\".\"JOB\"\nFROM \"EMP\"\nLEFT JOIN \"DEPT\"\n  ON \"EMP\".\"JOB\" = \"DEPT\".\"NAME\"\n  AND (\"EMP\".\"DEPTNO\" + \"EMP\".\"EMPNO\") = (\"DEPT\".\"DEPTNO\" + 5)\nWHERE \"EMP\".\"ENAME\" = 'A'\nGROUP BY \"EMP\".\"JOB\"",
    "original_execution_time": 1.2025135358174641,
    "rewrite_execution_time": 1.1148041884104412,
    "speed_up": 0.07293834521987187,
    "times_up": 1.0786769087511991
  },
  {
    "id": 14,
    "equivalence": true,
    "original_query": "SELECT \"t6\".\"NAME\" FROM (SELECT \"JOB\" FROM \"EMP\" WHERE \"ENAME\" = 'A' GROUP BY \"JOB\") AS \"t5\" LEFT JOIN (SELECT \"NAME\" FROM \"DEPT\" GROUP BY \"NAME\") AS \"t6\" ON \"t5\".\"JOB\" = \"t6\".\"NAME\" GROUP BY \"t6\".\"NAME\"",
    "rewritten_query": "SELECT DISTINCT d.\"NAME\"\nFROM \"EMP\" e\nLEFT JOIN \"DEPT\" d ON e.\"JOB\" = d.\"NAME\"\nWHERE e.\"ENAME\" = 'A';",
    "original_execution_time": 1.1280627250671387,
    "rewrite_execution_time": 1.1101382573445637,
    "speed_up": 0.01588960199133265,
    "times_up": 1.0161461580158944
  },
  {
    "id": 15,
    "equivalence": true,
    "original_query": "SELECT \"t8\".\"NAME\" FROM (SELECT \"JOB\", \"DEPTNO\" + \"EMPNO\" AS \"f9\" FROM \"EMP\" WHERE \"ENAME\" = 'A' GROUP BY \"JOB\", \"DEPTNO\" + \"EMPNO\") AS \"t6\" LEFT JOIN (SELECT \"NAME\", \"DEPTNO\" + 5 AS \"f2\" FROM \"DEPT\" GROUP BY \"NAME\", \"DEPTNO\" + 5) AS \"t8\" ON \"t6\".\"JOB\" = \"t8\".\"NAME\" AND \"t6\".\"f9\" = \"t8\".\"f2\" GROUP BY \"t8\".\"NAME\"",
    "rewritten_query": "/*+ NoHashJoin(t6 t8) */\nSELECT \"t8\".\"NAME\"\nFROM (\n    SELECT \"JOB\", \"DEPTNO\" + \"EMPNO\" AS \"f9\"\n    FROM \"EMP\"\n    WHERE \"ENAME\" = 'A'\n    GROUP BY \"JOB\", \"DEPTNO\" + \"EMPNO\"\n) AS \"t6\"\nLEFT JOIN (\n    SELECT \"NAME\", \"DEPTNO\" + 5 AS \"f2\"\n    FROM \"DEPT\"\n) AS \"t8\" ON \"t6\".\"JOB\" = \"t8\".\"NAME\" AND \"t6\".\"f9\" = \"t8\".\"f2\"\nGROUP BY \"t8\".\"NAME\"",
    "original_execution_time": 1.3063546021779378,
    "rewrite_execution_time": 1.194821,
    "speed_up": 0.08537773893243875,
    "times_up": 1.09334754091026
  },
  {
    "id": 16,
    "equivalence": true,
    "original_query": "SELECT \"t6\".\"JOB\", \"t8\".\"NAME\" FROM (SELECT \"JOB\", \"DEPTNO\" + \"EMPNO\" AS \"f9\" FROM \"EMP\" WHERE \"ENAME\" = 'A' GROUP BY \"JOB\", \"DEPTNO\" + \"EMPNO\") AS \"t6\" LEFT JOIN (SELECT \"NAME\", \"DEPTNO\" + 5 AS \"f2\" FROM \"DEPT\" GROUP BY \"NAME\", \"DEPTNO\" + 5) AS \"t8\" ON \"t6\".\"JOB\" = \"t8\".\"NAME\" AND \"t6\".\"f9\" = \"t8\".\"f2\" GROUP BY \"t6\".\"JOB\", \"t8\".\"NAME\"",
    "rewritten_query": "SELECT \"t6\".\"JOB\", \"t8\".\"NAME\" FROM (SELECT \"JOB\", \"DEPTNO\" + \"EMPNO\" AS \"f9\" FROM \"EMP\" WHERE \"ENAME\" = 'A' GROUP BY \"JOB\", \"DEPTNO\" + \"EMPNO\") AS \"t6\" LEFT JOIN (SELECT \"NAME\", \"DEPTNO\" + 5 AS \"f2\" FROM \"DEPT\" GROUP BY \"NAME\", \"DEPTNO\" + 5) AS \"t8\" ON \"t6\".\"JOB\" = \"t8\".\"NAME\" AND \"t6\".\"f9\" = \"t8\".\"f2\" GROUP BY \"t6\".\"JOB\", \"t8\".\"NAME\"",
    "original_execution_time": 1.2759485244750977,
    "rewrite_execution_time": 1.3028875986735027,
    "speed_up": -0.021112978840182657,
    "times_up": 0.9793235623504036
  },
  {
    "id": 17,
    "equivalence": true,
    "original_query": "SELECT COUNT(\"C\") FILTER (WHERE \"g_0_f_1\"), COUNT(\"D\") FILTER (WHERE \"g_0_f_0\") FROM (SELECT \"SAL\" > 1000 AS \"C\", \"SAL\" < 500 AS \"D\", GROUPING(\"SAL\" > 1000, \"SAL\" < 500) = 0 AND \"SAL\" > 1000 AS \"g_0_f_0\", GROUPING(\"SAL\" > 1000, \"SAL\" < 500) = 0 AND \"SAL\" < 500 AS \"g_0_f_1\" FROM \"EMP\" GROUP BY \"SAL\" > 1000, \"SAL\" < 500) AS \"t3\"",
    "rewritten_query": "SELECT COUNT(\"C\") FILTER (WHERE \"g_0_f_1\"), COUNT(\"D\") FILTER (WHERE \"g_0_f_0\") FROM (SELECT \"SAL\" > 1000 AS \"C\", \"SAL\" < 500 AS \"D\", GROUPING(\"SAL\" > 1000, \"SAL\" < 500) = 0 AND \"SAL\" > 1000 AS \"g_0_f_0\", GROUPING(\"SAL\" > 1000, \"SAL\" < 500) = 0 AND \"SAL\" < 500 AS \"g_0_f_1\" FROM \"EMP\" GROUP BY \"SAL\" > 1000, \"SAL\" < 500) AS \"t3\"",
    "original_execution_time": 2.3008159001668296,
    "rewrite_execution_time": 2.3566036224365234,
    "speed_up": -0.024246930084953235,
    "times_up": 0.9763270658932391
  },
  {
    "id": 18,
    "equivalence": true,
    "original_query": "SELECT * FROM (SELECT \"DEPTNO\", \"NAME\" FROM \"DEPT\" WHERE EXISTS (SELECT 1 FROM (SELECT \"DEPTNO\" FROM \"EMP\") AS \"t4\" WHERE \"DEPTNO\" = \"t4\".\"DEPTNO\") ORDER BY \"DEPTNO\") AS \"t3\" ORDER BY \"DEPTNO\" OFFSET 2 ROWS FETCH NEXT 10 ROWS ONLY",
    "rewritten_query": "SELECT \"DEPTNO\", \"NAME\"\nFROM \"DEPT\"\nWHERE EXISTS (SELECT 1 FROM \"EMP\" WHERE \"DEPT\".\"DEPTNO\" = \"EMP\".\"DEPTNO\")\nORDER BY \"DEPTNO\"\nOFFSET 2 ROWS FETCH NEXT 10 ROWS ONLY;",
    "original_execution_time": 0.00021441777547200522,
    "rewrite_execution_time": 0.5200907389322916,
    "speed_up": -2424.595255744996,
    "times_up": 0.00041226993565043917
  },
  {
    "id": 19,
    "equivalence": true,
    "original_query": "SELECT \"t0\".\"SAL\" + \"t1\".\"COMM\", SUM(\"t1\".\"EXPR0\") OVER (PARTITION BY \"t1\".\"JOB\" RANGE BETWEEN UNBOUNDED PRECEDING AND UNBOUNDED FOLLOWING) FROM (SELECT \"ENAME\", \"SAL\", \"DEPTNO\" = 10 AS \"EXPR0\" FROM \"EMP\") AS \"t0\" INNER JOIN (SELECT \"ENAME\", \"JOB\", \"COMM\", \"SAL\" + \"SAL\" + 100 AS \"EXPR0\" FROM \"BONUS\") AS \"t1\" ON \"t0\".\"ENAME\" = \"t1\".\"ENAME\" AND \"t0\".\"EXPR0\"",
    "rewritten_query": "/*+ HashJoin(t0 t1) */\nSELECT \"t0\".\"SAL\" + \"t1\".\"COMM\", \n       SUM(\"t1\".\"EXPR0\") OVER (PARTITION BY \"t1\".\"JOB\") \nFROM \n  (SELECT \"ENAME\", \"SAL\" FROM \"EMP\" WHERE \"DEPTNO\" = 10) AS \"t0\" \nINNER JOIN \n  (SELECT \"ENAME\", \"JOB\", \"COMM\", 2 * \"SAL\" + 100 AS \"EXPR0\" FROM \"BONUS\") AS \"t1\" \n  ON \"t0\".\"ENAME\" = \"t1\".\"ENAME\"",
    "original_execution_time": 8.872784614562988,
    "rewrite_execution_time": 6.32822515,
    "speed_up": 0.2867825124918031,
    "times_up": 1.4020968603752963
  },
  {
    "id": 20,
    "equivalence": true,
    "original_query": "SELECT \"t2\".\"JOB\", \"t2\".\"MIN_SAL\", \"t2\".\"MIN_DEPTNO\", CAST(\"t2\".\"SUM_SAL_2\" * \"t3\".\"f1\" AS INTEGER) + 1 AS \"SUM_SAL_PLUS\", \"t2\".\"MAX_SAL\", CAST(\"t2\".\"SUM_SAL_2\" * \"t3\".\"f1\" AS INTEGER) AS \"SUM_SAL_2\", \"t2\".\"COUNT_SAL\" * \"t3\".\"f1\" AS \"COUNT_SAL\", \"t2\".\"COUNT_MGR\" * \"t3\".\"f1\" AS \"COUNT_MGR\" FROM (SELECT \"JOB\", MIN(\"SAL\") AS \"MIN_SAL\", MIN(\"DEPTNO\") AS \"MIN_DEPTNO\", SUM(\"SAL\") AS \"SUM_SAL_2\", MAX(\"SAL\") AS \"MAX_SAL\", COUNT(*) AS \"COUNT_SAL\", COUNT(\"MGR\") AS \"COUNT_MGR\" FROM \"EMP\" GROUP BY \"JOB\") AS \"t2\" INNER JOIN (SELECT \"NAME\", COUNT(*) AS \"f1\" FROM \"DEPT\" GROUP BY \"NAME\") AS \"t3\" ON \"t2\".\"JOB\" = \"t3\".\"NAME\"",
    "rewritten_query": "/*+ NOT MATERIALIZED(combined) */\nWITH combined AS ( /*+ Rows(t2 t3 #30000) */\n  SELECT \n    \"t2\".\"JOB\", \n    \"t2\".\"MIN_SAL\", \n    \"t2\".\"MIN_DEPTNO\", \n    \"t2\".\"MAX_SAL\", \n    \"t2\".\"COUNT_SAL\", \n    \"t2\".\"COUNT_MGR\",\n    \"t3\".\"f1\",\n    CAST(\"t2\".\"SUM_SAL_2\" * \"t3\".\"f1\" AS INTEGER) AS sum_sal_casted\n  FROM (\n    SELECT \n      \"JOB\", \n      MIN(\"SAL\") AS \"MIN_SAL\", \n      MIN(\"DEPTNO\") AS \"MIN_DEPTNO\", \n      SUM(\"SAL\") AS \"SUM_SAL_2\", \n      MAX(\"SAL\") AS \"MAX_SAL\", \n      COUNT(*) AS \"COUNT_SAL\", \n      COUNT(\"MGR\") AS \"COUNT_MGR\" \n    FROM \"EMP\" \n    GROUP BY \"JOB\"\n  ) AS \"t2\" \n  INNER JOIN (\n    SELECT \n      \"NAME\", \n      COUNT(*) AS \"f1\" \n    FROM \"DEPT\" \n    GROUP BY \"NAME\"\n  ) AS \"t3\" ON \"t2\".\"JOB\" = \"t3\".\"NAME\"\n)\nSELECT \n  \"JOB\", \n  \"MIN_SAL\", \n  \"MIN_DEPTNO\", \n  sum_sal_casted + 1 AS \"SUM_SAL_PLUS\", \n  \"MAX_SAL\", \n  sum_sal_casted AS \"SUM_SAL_2\", \n  \"COUNT_SAL\" * \"f1\" AS \"COUNT_SAL\", \n  \"COUNT_MGR\" * \"f1\" AS \"COUNT_MGR\" \nFROM combined",
    "original_execution_time": 7.0040468374888105,
    "rewrite_execution_time": 7.04368184,
    "speed_up": -0.005658871711000667,
    "times_up": 0.9943729709246508
  },
  {
    "id": 21,
    "equivalence": true,
    "original_query": "SELECT \"EMP0\".\"ENAME\" FROM (SELECT * FROM \"EMP\" WHERE \"ENAME\" = 'A') AS \"t0\" LEFT JOIN \"EMP\" AS \"EMP0\" ON \"t0\".\"JOB\" = \"EMP0\".\"JOB\" GROUP BY \"EMP0\".\"ENAME\"",
    "rewritten_query": "SELECT DISTINCT \"EMP0\".\"ENAME\"\nFROM (SELECT \"JOB\" FROM \"EMP\" WHERE \"ENAME\" = 'A') AS \"t0\"\nLEFT JOIN \"EMP\" AS \"EMP0\" ON \"t0\".\"JOB\" = \"EMP0\".\"JOB\";",
    "original_execution_time": 8.68344259262085,
    "rewrite_execution_time": 7.867865324020386,
    "speed_up": 0.09392326371726552,
    "times_up": 1.1036592817762816
  },
  {
    "id": 22,
    "equivalence": true,
    "original_query": "SELECT \"t0\".\"JOB\" FROM (SELECT \"EMPNO\", \"ENAME\", \"JOB\", \"MGR\", \"HIREDATE\", \"SAL\", \"COMM\", \"DEPTNO\", \"SLACKER\", \"DEPTNO\" + \"EMPNO\" AS \"f9\" FROM \"EMP\" WHERE \"ENAME\" = 'A') AS \"t0\" LEFT JOIN (SELECT \"DEPTNO\", \"NAME\", \"DEPTNO\" + 5 AS \"f2\" FROM \"DEPT\") AS \"t1\" ON \"t0\".\"JOB\" = \"t1\".\"NAME\" AND \"t0\".\"f9\" = \"t1\".\"f2\" GROUP BY \"t0\".\"JOB\"",
    "rewritten_query": "SELECT \"JOB\" FROM \"EMP\" WHERE \"ENAME\" = 'A' GROUP BY \"JOB\"",
    "original_execution_time": 1.0070033073425293,
    "rewrite_execution_time": 0.9895623524983724,
    "speed_up": 0.017319659942511365,
    "times_up": 1.017624917520481
  },
  {
    "id": 23,
    "equivalence": true,
    "original_query": "SELECT \"t0\".\"SAL\" FROM (SELECT \"EMPNO\", \"ENAME\", \"JOB\", \"MGR\", \"HIREDATE\", \"SAL\", \"COMM\", \"SLACKER\", \"SAL\" AS \"SAL0\", \"SAL\" = 4 AS \"f9\" FROM \"EMPNULLABLES\" WHERE \"DEPTNO\" = 20 AND \"SAL\" > 1000) AS \"t0\" INNER JOIN (SELECT \"t2\".\"SAL\", \"t5\".\"SAL\" AS \"SAL0\", \"t5\".\"f9\" FROM (SELECT \"EMPNO\", \"ENAME\", \"JOB\", \"MGR\", \"HIREDATE\", \"SAL\", \"COMM\", \"SLACKER\" FROM \"EMPNULLABLES\" WHERE \"DEPTNO\" = 20 AND \"SAL\" > 1000) AS \"t2\" INNER JOIN (SELECT \"SAL\", \"SAL\" = 4 AS \"f9\" FROM \"EMPNULLABLES\" WHERE \"DEPTNO\" = 20 AND \"SAL\" > 1000 GROUP BY \"SAL\", \"SAL\" = 4) AS \"t5\" ON \"t2\".\"SAL\" = \"t5\".\"SAL\" OR \"t5\".\"f9\" GROUP BY \"t2\".\"SAL\", \"t5\".\"SAL\", \"t5\".\"f9\" HAVING \"t5\".\"SAL\" = \"t2\".\"SAL\") AS \"t8\" ON \"t0\".\"SAL\" = \"t8\".\"SAL0\" AND \"t0\".\"f9\" = \"t8\".\"f9\"",
    "rewritten_query": "SELECT \"SAL\" FROM \"EMPNULLABLES\" WHERE \"DEPTNO\" = 20 AND \"SAL\" > 1000",
    "original_execution_time": 2.8489842414855957,
    "rewrite_execution_time": 1.5090413093566895,
    "speed_up": 0.470323040969225,
    "times_up": 1.887943175458947
  },
  {
    "id": 24,
    "equivalence": true,
    "original_query": "SELECT SUM(CAST(\"t3\".\"f1\" * \"t4\".\"SAL\" AS INTEGER)) FROM (SELECT \"SAL\", COUNT(*) AS \"f1\" FROM \"EMP\" GROUP BY \"SAL\") AS \"t3\" INNER JOIN (SELECT \"SAL\" FROM \"EMP\" GROUP BY \"SAL\") AS \"t4\" ON \"t3\".\"SAL\" = \"t4\".\"SAL\"",
    "rewritten_query": "SELECT SUM(CAST(\"t3\".\"f1\" * \"t4\".\"SAL\" AS INTEGER)) FROM (SELECT \"SAL\", COUNT(*) AS \"f1\" FROM \"EMP\" GROUP BY \"SAL\") AS \"t3\" INNER JOIN (SELECT \"SAL\" FROM \"EMP\" GROUP BY \"SAL\") AS \"t4\" ON \"t3\".\"SAL\" = \"t4\".\"SAL\"",
    "original_execution_time": 4.792720238367717,
    "rewrite_execution_time": 5.059259096781413,
    "speed_up": -0.05561327287162351,
    "times_up": 0.9473166221940951
  },
  {
    "id": 25,
    "equivalence": true,
    "original_query": "SELECT CASE WHEN COALESCE(SUM(\"t5\".\"f2\" * \"t6\".\"f1\"), 0) = 0 THEN NULL ELSE COALESCE(SUM(CAST(\"t5\".\"EXPR0\" * \"t6\".\"f1\" AS INTEGER)), 0) END FROM (SELECT \"JOB\", COALESCE(SUM(\"SAL\"), 0) AS \"EXPR0\", COUNT(*) AS \"f2\" FROM \"EMP\" WHERE \"ENAME\" = 'A' GROUP BY \"JOB\") AS \"t5\" INNER JOIN (SELECT \"NAME\", COUNT(*) AS \"f1\" FROM \"DEPT\" GROUP BY \"NAME\") AS \"t6\" ON \"t5\".\"JOB\" = \"t6\".\"NAME\"",
    "rewritten_query": "SELECT CASE WHEN COALESCE(SUM(\"t5\".\"f2\" * \"t6\".\"f1\"), 0) = 0 THEN NULL ELSE COALESCE(SUM(CAST(\"t5\".\"EXPR0\" * \"t6\".\"f1\" AS INTEGER)), 0) END FROM (SELECT \"JOB\", COALESCE(SUM(\"SAL\"), 0) AS \"EXPR0\", COUNT(*) AS \"f2\" FROM \"EMP\" WHERE \"ENAME\" = 'A' GROUP BY \"JOB\") AS \"t5\" INNER JOIN (SELECT \"NAME\", COUNT(*) AS \"f1\" FROM \"DEPT\" GROUP BY \"NAME\") AS \"t6\" ON \"t5\".\"JOB\" = \"t6\".\"NAME\"",
    "original_execution_time": 1.0187859535217285,
    "rewrite_execution_time": 1.115596850713094,
    "speed_up": -0.09502574790780202,
    "times_up": 0.9132205355998598
  },
  {
    "id": 26,
    "equivalence": true,
    "original_query": "SELECT * FROM (SELECT \"DEPT\".\"DEPTNO\", \"DEPT\".\"NAME\" FROM \"DEPT\" INNER JOIN (SELECT \"DEPTNO\" FROM \"EMP\" GROUP BY \"DEPTNO\") AS \"t0\" ON \"DEPT\".\"DEPTNO\" = \"t0\".\"DEPTNO\") AS \"t1\" WHERE \"t1\".\"DEPTNO\" <= 10",
    "rewritten_query": "SELECT \"DEPT\".\"DEPTNO\", \"DEPT\".\"NAME\"\nFROM \"DEPT\"\nWHERE \"DEPT\".\"DEPTNO\" <= 10\nAND EXISTS (\n    SELECT 1\n    FROM \"EMP\"\n    WHERE \"EMP\".\"DEPTNO\" = \"DEPT\".\"DEPTNO\"\n);",
    "original_execution_time": 6.319442351659139,
    "rewrite_execution_time": 5.817257801691691,
    "speed_up": 0.07946659246533062,
    "times_up": 1.0863266795261177
  },
  {
    "id": 27,
    "equivalence": true,
    "original_query": "SELECT \"t0\".\"SAL\" + \"t1\".\"COMM\" FROM (SELECT \"ENAME\", \"SAL\", \"DEPTNO\" = 10 AS \"EXPR0\" FROM \"EMP\") AS \"t0\" INNER JOIN (SELECT \"ENAME\", \"COMM\" FROM \"BONUS\") AS \"t1\" ON \"t0\".\"ENAME\" = \"t1\".\"ENAME\" AND \"t0\".\"EXPR0\"",
    "rewritten_query": "/*+ NoHashJoin(t0 t1) */\nSELECT \"t0\".\"SAL\" + \"t1\".\"COMM\" FROM (SELECT \"ENAME\", \"SAL\", \"DEPTNO\" = 10 AS \"EXPR0\" FROM \"EMP\") AS \"t0\" INNER JOIN (SELECT \"ENAME\", \"COMM\" FROM \"BONUS\") AS \"t1\" ON \"t0\".\"ENAME\" = \"t1\".\"ENAME\" AND \"t0\".\"EXPR0\"",
    "original_execution_time": 6.00437315305074,
    "rewrite_execution_time": 5.89384346,
    "speed_up": 0.01840819853019651,
    "times_up": 1.018753415118823
  },
  {
    "id": 28,
    "equivalence": true,
    "original_query": "SELECT \"t5\".\"JOB\" FROM (SELECT \"JOB\" FROM \"EMP\" WHERE \"ENAME\" = 'A' GROUP BY \"JOB\") AS \"t5\" FULL JOIN (SELECT \"NAME\" FROM \"DEPT\" GROUP BY \"NAME\") AS \"t6\" ON \"t5\".\"JOB\" = \"t6\".\"NAME\" GROUP BY \"t5\".\"JOB\"",
    "rewritten_query": "SELECT \"t5\".\"JOB\"\nFROM (SELECT \"JOB\" FROM \"EMP\" WHERE \"ENAME\" = 'A' GROUP BY \"JOB\") AS \"t5\"\nFULL JOIN (SELECT \"NAME\" FROM \"DEPT\" GROUP BY \"NAME\") AS \"t6\" \nON \"t5\".\"JOB\" = \"t6\".\"NAME\";",
    "original_execution_time": 1.0957175095876057,
    "rewrite_execution_time": 1.1975716749827068,
    "speed_up": -0.0929565919170497,
    "times_up": 0.9149494201283845
  },
  {
    "id": 29,
    "equivalence": true,
    "original_query": "SELECT MIN(\"EXPR0\") FILTER (WHERE \"g_3\"), COUNT(\"SAL\") FILTER (WHERE \"g_0_f_1\") FROM (SELECT \"SAL\", SUM(\"COMM\") AS \"EXPR0\", GROUPING(\"SAL\", \"SAL\" > 1000) = 0 AND \"SAL\" > 1000 IS TRUE AS \"g_0_f_1\", GROUPING(\"SAL\", \"SAL\" > 1000) = 3 AS \"g_3\" FROM \"EMP\" GROUP BY GROUPING SETS((\"SAL\", \"SAL\" > 1000), ())) AS \"t3\"",
    "rewritten_query": "SELECT MIN(\"EXPR0\") FILTER (WHERE \"g_3\"), COUNT(\"SAL\") FILTER (WHERE \"g_0_f_1\") FROM (SELECT \"SAL\", SUM(\"COMM\") AS \"EXPR0\", GROUPING(\"SAL\", \"SAL\" > 1000) = 0 AND \"SAL\" > 1000 IS TRUE AS \"g_0_f_1\", GROUPING(\"SAL\", \"SAL\" > 1000) = 3 AS \"g_3\" FROM \"EMP\" GROUP BY GROUPING SETS((\"SAL\", \"SAL\" > 1000), ())) AS \"t3\"",
    "original_execution_time": 7.251816987991333,
    "rewrite_execution_time": 7.283604701360066,
    "speed_up": -0.004383413621906397,
    "times_up": 0.995635716836363
  },
  {
    "id": 30,
    "equivalence": true,
    "original_query": "SELECT \"ENAME\", \"SAL\", \"DEPTNO\" FROM (SELECT \"ENAME\", \"SAL\", \"DEPTNO\" FROM \"EMP\" GROUP BY \"ENAME\", \"SAL\", \"DEPTNO\" HAVING \"SAL\" > 5000) AS \"t4\" GROUP BY ROLLUP(\"ENAME\", \"SAL\", \"DEPTNO\")",
    "rewritten_query": "SELECT \"ENAME\", \"SAL\", \"DEPTNO\" \nFROM \"EMP\" \nWHERE \"SAL\" > 5000 \nGROUP BY ROLLUP(\"ENAME\", \"SAL\", \"DEPTNO\")",
    "original_execution_time": 1.1882507006327312,
    "rewrite_execution_time": 1.1954856713612874,
    "speed_up": -0.006088757805658032,
    "times_up": 0.9939480908037001
  },
  {
    "id": 31,
    "equivalence": true,
    "original_query": "SELECT \"t6\".\"JOB\" FROM (SELECT \"JOB\", \"DEPTNO\" + \"EMPNO\" AS \"f9\" FROM \"EMP\" WHERE \"ENAME\" = 'A' GROUP BY \"JOB\", \"DEPTNO\" + \"EMPNO\") AS \"t6\" FULL JOIN (SELECT \"NAME\", \"DEPTNO\" + 5 AS \"f2\" FROM \"DEPT\" GROUP BY \"NAME\", \"DEPTNO\" + 5) AS \"t8\" ON \"t6\".\"JOB\" = \"t8\".\"NAME\" AND \"t6\".\"f9\" = \"t8\".\"f2\" GROUP BY \"t6\".\"JOB\"",
    "rewritten_query": "SELECT \"t6\".\"JOB\"\nFROM (\n    SELECT \"JOB\", \"DEPTNO\" + \"EMPNO\" AS \"f9\"\n    FROM \"EMP\"\n    WHERE \"ENAME\" = 'A'\n    GROUP BY \"JOB\", \"DEPTNO\" + \"EMPNO\"\n) AS \"t6\"\nFULL JOIN (\n    SELECT \"NAME\", \"DEPTNO\" + 5 AS \"f2\"\n    FROM \"DEPT\"\n) AS \"t8\"\nON \"t6\".\"JOB\" = \"t8\".\"NAME\" AND \"t6\".\"f9\" = \"t8\".\"f2\"\nGROUP BY \"t6\".\"JOB\"",
    "original_execution_time": 1.2429282665252686,
    "rewrite_execution_time": 1.1012742519378662,
    "speed_up": 0.11396797257126547,
    "times_up": 1.1286273735521735
  },
  {
    "id": 32,
    "equivalence": true,
    "original_query": "SELECT \"MGR\", SUM(\"SUM_SAL\") FROM (SELECT \"MGR\", SUM(\"SAL\") AS \"SUM_SAL\" FROM \"EMP\" GROUP BY \"MGR\", \"DEPTNO\" HAVING \"DEPTNO\" = 100) AS \"t2\" GROUP BY \"MGR\"",
    "rewritten_query": "SELECT \"MGR\", SUM(\"SAL\") AS \"SUM_SAL\"\nFROM \"EMP\"\nWHERE \"DEPTNO\" = 100\nGROUP BY \"MGR\"",
    "original_execution_time": 0.8748223781585693,
    "rewrite_execution_time": 1.0151275793711345,
    "speed_up": -0.16038135822256436,
    "times_up": 0.8617856473769697
  },
  {
    "id": 33,
    "equivalence": true,
    "original_query": "SELECT \"t5\".\"ENAME\" FROM (SELECT \"ENAME\", \"JOB\" FROM \"EMP\" WHERE \"ENAME\" = 'A' GROUP BY \"ENAME\", \"JOB\") AS \"t5\" LEFT JOIN (SELECT \"NAME\" FROM \"DEPT\" GROUP BY \"NAME\") AS \"t6\" ON \"t5\".\"JOB\" = \"t6\".\"NAME\" GROUP BY \"t5\".\"ENAME\"",
    "rewritten_query": "SELECT \"ENAME\" \nFROM \"EMP\" \nWHERE \"ENAME\" = 'A' \nGROUP BY \"ENAME\"",
    "original_execution_time": 0.9402305285135905,
    "rewrite_execution_time": 1.0755844910939534,
    "speed_up": -0.14395827244021087,
    "times_up": 0.8741577591522379
  },
  {
    "id": 35,
    "equivalence": true,
    "original_query": "SELECT COALESCE(SUM(\"t1\".\"EXPR0\" * \"t2\".\"EXPR0\"), 0) FROM (SELECT \"JOB\", COUNT(*) AS \"EXPR0\" FROM \"EMP\" GROUP BY \"JOB\") AS \"t1\" INNER JOIN (SELECT \"NAME\", COUNT(*) AS \"EXPR0\" FROM \"DEPT\" GROUP BY \"NAME\") AS \"t2\" ON \"t1\".\"JOB\" = \"t2\".\"NAME\"",
    "rewritten_query": "/*+ Rows(t1 t2 #28268) */\nSELECT COALESCE(SUM(\"t1\".\"EXPR0\" * \"t2\".\"EXPR0\"), 0) FROM (SELECT \"JOB\", COUNT(*) AS \"EXPR0\" FROM \"EMP\" GROUP BY \"JOB\") AS \"t1\" INNER JOIN (SELECT \"NAME\", COUNT(*) AS \"EXPR0\" FROM \"DEPT\" GROUP BY \"NAME\") AS \"t2\" ON \"t1\".\"JOB\" = \"t2\".\"NAME\"",
    "original_execution_time": 3.544041713078817,
    "rewrite_execution_time": 3.66238384,
    "speed_up": -0.033391854978584795,
    "times_up": 0.9676871316357755
  },
  {
    "id": 36,
    "equivalence": true,
    "original_query": "SELECT \"t6\".\"JOB\", CAST(\"t6\".\"EXPR1\" * \"t7\".\"f1\" AS INTEGER) FROM (SELECT \"JOB\", SUM(\"SAL\") AS \"EXPR1\" FROM \"EMP\" WHERE \"ENAME\" = 'A' GROUP BY \"JOB\") AS \"t6\" INNER JOIN (SELECT \"NAME\", COUNT(*) AS \"f1\" FROM \"DEPT\" GROUP BY \"NAME\") AS \"t7\" ON \"t6\".\"JOB\" = \"t7\".\"NAME\"",
    "rewritten_query": "SELECT \"t6\".\"JOB\", CAST(\"t6\".\"EXPR1\" * \"t7\".\"f1\" AS INTEGER) FROM (SELECT \"JOB\", SUM(\"SAL\") AS \"EXPR1\" FROM \"EMP\" WHERE \"ENAME\" = 'A' GROUP BY \"JOB\") AS \"t6\" INNER JOIN (SELECT \"NAME\", COUNT(*) AS \"f1\" FROM \"DEPT\" GROUP BY \"NAME\") AS \"t7\" ON \"t6\".\"JOB\" = \"t7\".\"NAME\"",
    "original_execution_time": 1.0763078530629475,
    "rewrite_execution_time": 1.1436389287312825,
    "speed_up": -0.06255745089727328,
    "times_up": 0.9411255825796084
  },
  {
    "id": 37,
    "equivalence": true,
    "original_query": "SELECT \"NAME\", CAST(SUM(\"CN\") FILTER (WHERE \"g_1\") AS BIGINT), CAST(SUM(\"SM\") FILTER (WHERE \"g_2\") AS INTEGER) FROM (SELECT \"NAME\", \"CN\", \"SM\", GROUPING(\"NAME\", \"CN\", \"SM\") = 1 AS \"g_1\", GROUPING(\"NAME\", \"CN\", \"SM\") = 2 AS \"g_2\" FROM (SELECT \"NAME\", COUNT(*) AS \"CN\", SUM(\"DEPTNO\") AS \"SM\" FROM \"DEPT\" GROUP BY \"NAME\") AS \"t3\" GROUP BY GROUPING SETS((\"NAME\", \"CN\"), (\"NAME\", \"SM\"))) AS \"t5\" GROUP BY \"NAME\"",
    "rewritten_query": "SELECT \"NAME\", CAST(SUM(\"CN\") FILTER (WHERE \"g_1\") AS BIGINT), CAST(SUM(\"SM\") FILTER (WHERE \"g_2\") AS INTEGER) FROM (SELECT \"NAME\", \"CN\", \"SM\", GROUPING(\"NAME\", \"CN\", \"SM\") = 1 AS \"g_1\", GROUPING(\"NAME\", \"CN\", \"SM\") = 2 AS \"g_2\" FROM (SELECT \"NAME\", COUNT(*) AS \"CN\", SUM(\"DEPTNO\") AS \"SM\" FROM \"DEPT\" GROUP BY \"NAME\") AS \"t3\" GROUP BY GROUPING SETS((\"NAME\", \"CN\"), (\"NAME\", \"SM\"))) AS \"t5\" GROUP BY \"NAME\"",
    "original_execution_time": 0.24882292747497559,
    "rewrite_execution_time": 0.27261026700337726,
    "speed_up": -0.09559946814303917,
    "times_up": 0.9127423196863419
  },
  {
    "id": 38,
    "equivalence": true,
    "original_query": "SELECT SUM(\"SAL\") AS \"SUM_SAL\", COUNT(DISTINCT CASE WHEN \"JOB\" = 'CLERK' THEN \"DEPTNO\" ELSE NULL END) AS \"COUNT_DISTINCT_CLERK\", SUM(CASE WHEN \"DEPTNO\" = 10 THEN \"SAL\" ELSE NULL END) AS \"SUM_SAL_D10\", SUM(CASE WHEN \"DEPTNO\" = 20 THEN \"SAL\" ELSE 0 END) AS \"SUM_SAL_D20\", SUM(CASE WHEN \"DEPTNO\" = 30 THEN 1 ELSE 0 END) AS \"COUNT_D30\", COUNT(CASE WHEN \"DEPTNO\" = 40 THEN 'x' ELSE NULL END) AS \"COUNT_D40\", SUM(CASE WHEN \"DEPTNO\" = 45 THEN 1 ELSE NULL END) AS \"COUNT_D45\", SUM(CASE WHEN \"DEPTNO\" = 50 THEN 1 ELSE NULL END) AS \"COUNT_D50\", SUM(CAST(NULL AS DECIMAL(19, 9))) AS \"SUM_NULL_D60\", SUM(CASE WHEN \"DEPTNO\" = 70 THEN NULL ELSE 1 END) AS \"SUM_NULL_D70\", COUNT(CASE WHEN \"DEPTNO\" = 20 THEN 1 ELSE NULL END) AS \"COUNT_D20\" FROM \"EMP\"",
    "rewritten_query": "SELECT SUM(\"SAL\") AS \"SUM_SAL\", COUNT(DISTINCT CASE WHEN \"JOB\" = 'CLERK' THEN \"DEPTNO\" ELSE NULL END) AS \"COUNT_DISTINCT_CLERK\", SUM(CASE WHEN \"DEPTNO\" = 10 THEN \"SAL\" ELSE NULL END) AS \"SUM_SAL_D10\", SUM(CASE WHEN \"DEPTNO\" = 20 THEN \"SAL\" ELSE 0 END) AS \"SUM_SAL_D20\", SUM(CASE WHEN \"DEPTNO\" = 30 THEN 1 ELSE 0 END) AS \"COUNT_D30\", COUNT(CASE WHEN \"DEPTNO\" = 40 THEN 'x' ELSE NULL END) AS \"COUNT_D40\", SUM(CASE WHEN \"DEPTNO\" = 45 THEN 1 ELSE NULL END) AS \"COUNT_D45\", SUM(CASE WHEN \"DEPTNO\" = 50 THEN 1 ELSE NULL END) AS \"COUNT_D50\", SUM(CAST(NULL AS DECIMAL(19, 9))) AS \"SUM_NULL_D60\", SUM(CASE WHEN \"DEPTNO\" = 70 THEN NULL ELSE 1 END) AS \"SUM_NULL_D70\", COUNT(CASE WHEN \"DEPTNO\" = 20 THEN 1 ELSE NULL END) AS \"COUNT_D20\" FROM \"EMP\"",
    "original_execution_time": 4.75327483812968,
    "rewrite_execution_time": 5.019550561904907,
    "speed_up": -0.05601942510019089,
    "times_up": 0.9469522778003103
  },
  {
    "id": 39,
    "equivalence": true,
    "original_query": "SELECT \"t6\".\"JOB\" FROM (SELECT \"JOB\", \"DEPTNO\" + \"EMPNO\" AS \"f9\" FROM \"EMP\" WHERE \"ENAME\" = 'A' GROUP BY \"JOB\", \"DEPTNO\" + \"EMPNO\") AS \"t6\" LEFT JOIN (SELECT \"NAME\", \"DEPTNO\" + 5 AS \"f2\" FROM \"DEPT\" GROUP BY \"NAME\", \"DEPTNO\" + 5) AS \"t8\" ON \"t6\".\"JOB\" = \"t8\".\"NAME\" AND \"t6\".\"f9\" = \"t8\".\"f2\" GROUP BY \"t6\".\"JOB\"",
    "rewritten_query": "SELECT \"t6\".\"JOB\" FROM (SELECT \"JOB\", \"DEPTNO\" + \"EMPNO\" AS \"f9\" FROM \"EMP\" WHERE \"ENAME\" = 'A' GROUP BY \"JOB\", \"DEPTNO\" + \"EMPNO\") AS \"t6\" LEFT JOIN (SELECT \"NAME\", \"DEPTNO\" + 5 AS \"f2\" FROM \"DEPT\" GROUP BY \"NAME\", \"DEPTNO\" + 5) AS \"t8\" ON \"t6\".\"JOB\" = \"t8\".\"NAME\" AND \"t6\".\"f9\" = \"t8\".\"f2\" GROUP BY \"t6\".\"JOB\"",
    "original_execution_time": 1.0398546854654949,
    "rewrite_execution_time": 1.0499656200408936,
    "speed_up": -0.009723411084956059,
    "times_up": 0.990370223193589
  },
  {
    "id": 40,
    "equivalence": true,
    "original_query": "SELECT \"t12\".\"SAL\" FROM (SELECT * FROM (SELECT \"EMPNO\", \"ENAME\", \"JOB\", \"MGR\", \"HIREDATE\", \"SAL\", \"COMM\", \"SLACKER\", \"SAL\" AS \"SAL0\", \"SAL\" = 4 AS \"f9\" FROM \"EMPNULLABLES\" WHERE \"DEPTNO\" = 20 AND \"SAL\" > 1000) AS \"t11\" WHERE \"SAL\" > 1000) AS \"t12\" INNER JOIN (SELECT \"t14\".\"SAL\", \"t17\".\"SAL\" AS \"SAL0\", \"t17\".\"f9\" FROM (SELECT \"EMPNO\", \"ENAME\", \"JOB\", \"MGR\", \"HIREDATE\", \"SAL\", \"COMM\", \"SLACKER\" FROM \"EMPNULLABLES\" WHERE \"DEPTNO\" = 20 AND \"SAL\" > 1000) AS \"t14\" INNER JOIN (SELECT \"SAL\", \"SAL\" = 4 AS \"f9\" FROM \"EMPNULLABLES\" WHERE \"DEPTNO\" = 20 AND \"SAL\" > 1000 GROUP BY \"SAL\", \"SAL\" = 4) AS \"t17\" ON \"t14\".\"SAL\" = \"t17\".\"SAL\" OR \"t17\".\"f9\" GROUP BY \"t14\".\"SAL\", \"t17\".\"SAL\", \"t17\".\"f9\" HAVING \"t17\".\"SAL\" = \"t14\".\"SAL\") AS \"t20\" ON \"t12\".\"SAL\" = \"t20\".\"SAL0\" AND \"t12\".\"f9\" = \"t20\".\"f9\"",
    "rewritten_query": "SELECT \"SAL\"\nFROM \"EMPNULLABLES\"\nWHERE \"DEPTNO\" = 20\n  AND \"SAL\" > 1000",
    "original_execution_time": 2.9184158643086753,
    "rewrite_execution_time": 1.5158530076344807,
    "speed_up": 0.48059047164151797,
    "times_up": 1.9252631024316285
  },
  {
    "id": 41,
    "equivalence": true,
    "original_query": "SELECT * FROM (SELECT \"DEPTNO\" FROM \"EMP\" WHERE \"DEPTNO\" < 4) AS \"t7\" INNER JOIN (SELECT * FROM (SELECT \"DEPTNO\" FROM \"EMP\" WHERE \"DEPTNO\" > 7 UNION ALL SELECT \"DEPTNO\" FROM \"EMP\") AS \"t11\" WHERE \"DEPTNO\" < 4) AS \"t12\" ON \"t7\".\"DEPTNO\" = \"t12\".\"DEPTNO\"",
    "rewritten_query": "WITH filtered_dept AS (\n  SELECT \"DEPTNO\" \n  FROM \"EMP\" \n  WHERE \"DEPTNO\" < 4\n)\nSELECT t7.\"DEPTNO\", t12.\"DEPTNO\"\nFROM filtered_dept AS t7\nINNER JOIN filtered_dept AS t12\nON t7.\"DEPTNO\" = t12.\"DEPTNO\"",
    "original_execution_time": 2.3123843669891357,
    "rewrite_execution_time": 0.958335796991984,
    "speed_up": 0.5855637969738591,
    "times_up": 2.4129166146639074
  },
  {
    "id": 42,
    "equivalence": true,
    "original_query": "SELECT COALESCE(SUM(\"EXPR0\"), 0), \"T2\" FROM (SELECT \"t5\".\"T2\", COUNT(CASE WHEN \"EMP1\".\"DEPTNO\" = 0 THEN 1 ELSE NULL END) AS \"EXPR0\" FROM \"EMP\" AS \"EMP1\", (VALUES (1)) AS \"t5\" (\"T2\") GROUP BY \"t5\".\"T2\" UNION ALL SELECT \"t8\".\"T2\", COUNT(CASE WHEN \"EMP2\".\"DEPTNO\" = 0 THEN 1 ELSE NULL END) AS \"EXPR0\" FROM \"EMP\" AS \"EMP2\", (VALUES (2)) AS \"t8\" (\"T2\") GROUP BY \"t8\".\"T2\") AS \"t11\" GROUP BY \"T2\"",
    "rewritten_query": "SELECT COUNT(CASE WHEN \"EMP\".\"DEPTNO\" = 0 THEN 1 END) AS \"EXPR0\", t.\"T2\"\nFROM \"EMP\"\nCROSS JOIN (VALUES (1), (2)) AS t(\"T2\")\nGROUP BY t.\"T2\"",
    "original_execution_time": 3.6212454636891684,
    "rewrite_execution_time": 7.229460875193278,
    "speed_up": -0.9964017760420515,
    "times_up": 0.5009011773083778
  },
  {
    "id": 43,
    "equivalence": true,
    "original_query": "SELECT \"t4\".\"NAME\" FROM (SELECT \"NAME\", \"DEPTNO\", \"DEPTNO\" - 10 AS \"DEPTNOMINUS\" FROM \"DEPT\") AS \"t4\" INNER JOIN (SELECT \"DEPTNO\", \"SAL\" + 1 AS \"f9\" FROM \"EMP\" GROUP BY \"DEPTNO\", \"SAL\" + 1) AS \"t6\" ON \"t4\".\"DEPTNOMINUS\" = \"t6\".\"f9\" AND \"t4\".\"DEPTNO\" = \"t6\".\"DEPTNO\"",
    "rewritten_query": "SELECT \"DEPT\".\"NAME\"\nFROM \"DEPT\"\nJOIN (\n    SELECT \"DEPTNO\"\n    FROM \"EMP\"\n    WHERE \"SAL\" = \"DEPTNO\" - 11\n) AS \"t6\" ON \"DEPT\".\"DEPTNO\" = \"t6\".\"DEPTNO\";",
    "original_execution_time": 49.964234352111816,
    "rewrite_execution_time": 1.1658231417338054,
    "speed_up": 0.9766668466583932,
    "times_up": 42.85747345674173
  },
  {
    "id": 44,
    "equivalence": true,
    "original_query": "SELECT \"t0\".\"JOB\", \"t1\".\"NAME\" FROM (SELECT \"EMPNO\", \"ENAME\", \"JOB\", \"MGR\", \"HIREDATE\", \"SAL\", \"COMM\", \"DEPTNO\", \"SLACKER\", \"DEPTNO\" + \"EMPNO\" AS \"f9\" FROM \"EMP\" WHERE \"ENAME\" = 'A') AS \"t0\" LEFT JOIN (SELECT \"DEPTNO\", \"NAME\", \"DEPTNO\" + 5 AS \"f2\" FROM \"DEPT\") AS \"t1\" ON \"t0\".\"JOB\" = \"t1\".\"NAME\" AND \"t0\".\"f9\" = \"t1\".\"f2\" GROUP BY \"t0\".\"JOB\", \"t1\".\"NAME\"",
    "rewritten_query": "/*+ NestLoop(t0 t1) NoHashJoin(t0 t1) */\nSELECT \"t0\".\"JOB\", \"t1\".\"NAME\"\nFROM (\n    SELECT \"JOB\", \"DEPTNO\" + \"EMPNO\" AS \"f9\"\n    FROM \"EMP\"\n    WHERE \"ENAME\" = 'A'\n) \"t0\"\nLEFT JOIN (\n    SELECT \"NAME\", \"DEPTNO\" + 5 AS \"f2\"\n    FROM \"DEPT\"\n) \"t1\"\nON \"t0\".\"JOB\" = \"t1\".\"NAME\" AND \"t0\".\"f9\" = \"t1\".\"f2\"",
    "original_execution_time": 1.132089614868164,
    "rewrite_execution_time": 1.12880034,
    "speed_up": 0.002905489834872439,
    "times_up": 1.0029139563052967
  },
  {
    "id": 45,
    "equivalence": true,
    "original_query": "SELECT CAST(1 AS INTEGER) AS \"DEPTNO\", \"ENAME\" FROM (SELECT \"ENAME\" FROM (SELECT \"ENAME\", \"DEPTNO\" FROM \"EMPNULLABLES\") AS \"t6\" WHERE \"DEPTNO\" = 1 UNION ALL SELECT \"ENAME\" FROM (SELECT \"ENAME\", \"DEPTNO\" FROM \"EMPNULLABLES\") AS \"t9\" WHERE \"DEPTNO\" = 1) AS \"t12\"",
    "rewritten_query": "SELECT CAST(1 AS INTEGER) AS \"DEPTNO\", \"ENAME\"\nFROM \"EMPNULLABLES\"\nCROSS JOIN (SELECT 1 UNION ALL SELECT 1) AS dummy\nWHERE \"DEPTNO\" = 1",
    "original_execution_time": 1.848918120066325,
    "rewrite_execution_time": 1.0401739279429119,
    "speed_up": 0.4374148229421872,
    "times_up": 1.777508616970257
  },
  {
    "id": 46,
    "equivalence": true,
    "original_query": "SELECT \"NAME\", \"DDEPTNO\", COUNT(*) AS \"C\" FROM (SELECT \"NAME\" AS \"NAME\", \"DEPTNO\" AS \"DDEPTNO\" FROM \"DEPT\") AS \"t3\" WHERE \"NAME\" = 'Charlie' GROUP BY GROUPING SETS((\"NAME\", \"DDEPTNO\"), \"NAME\")",
    "rewritten_query": "SELECT \"NAME\", \"DEPTNO\" AS \"DDEPTNO\", COUNT(*) AS \"C\"\nFROM \"DEPT\"\nWHERE \"NAME\" = 'Charlie'\nGROUP BY GROUPING SETS((\"NAME\", \"DEPTNO\"), \"NAME\");",
    "original_execution_time": 0.029622872670491535,
    "rewrite_execution_time": 0.028571367263793945,
    "speed_up": 0.03549640233727346,
    "times_up": 1.036802768204589
  },
  {
    "id": 47,
    "equivalence": true,
    "original_query": "SELECT \"NAME\" AS \"NAME\", \"DEPTNO\" AS \"DDEPTNO\", COUNT(*) AS \"C\" FROM \"DEPT\" GROUP BY GROUPING SETS((\"NAME\", \"DEPTNO\"), \"NAME\") HAVING \"NAME\" = 'Charlie'",
    "rewritten_query": "SELECT \"NAME\", \"DEPTNO\" AS \"DDEPTNO\", COUNT(*) AS \"C\"\nFROM \"DEPT\"\nWHERE \"NAME\" = 'Charlie'\nGROUP BY GROUPING SETS((\"NAME\", \"DEPTNO\"), \"NAME\")",
    "original_execution_time": 0.7131256262461344,
    "rewrite_execution_time": 0.035367727279663086,
    "speed_up": 0.9504046328192728,
    "times_up": 20.163173635875413
  },
  {
    "id": 48,
    "equivalence": true,
    "original_query": "SELECT \"t5\".\"JOB\" FROM (SELECT \"JOB\" FROM \"EMP\" WHERE \"ENAME\" = 'A' GROUP BY \"JOB\") AS \"t5\" RIGHT JOIN (SELECT \"NAME\" FROM \"DEPT\" GROUP BY \"NAME\") AS \"t6\" ON \"t5\".\"JOB\" = \"t6\".\"NAME\" GROUP BY \"t5\".\"JOB\"",
    "rewritten_query": "/*+ NoHashJoin(t5 t6) */\nSELECT t5.\"JOB\"  \nFROM (  \n  SELECT DISTINCT \"JOB\" AS \"JOB\" FROM \"EMP\" WHERE \"ENAME\" = 'A'  \n) AS t5  \nRIGHT JOIN (  \n  SELECT DISTINCT \"NAME\" FROM \"DEPT\"  \n) AS t6 ON t5.\"JOB\" = t6.\"NAME\"  \nGROUP BY t5.\"JOB\";",
    "original_execution_time": 1.1692471504211426,
    "rewrite_execution_time": 1.17467844,
    "speed_up": -0.004645116797506213,
    "times_up": 0.9953763605477789
  },
  {
    "id": 49,
    "equivalence": true,
    "original_query": "SELECT \"t2\".\"SAL\", \"t2\".\"EXPR1\", \"t5\".\"EXPR2\", \"t9\".\"EXPR3\" FROM (SELECT \"SAL\", SUM(\"COMM\") AS \"EXPR1\" FROM \"EMP\" GROUP BY \"SAL\") AS \"t2\" INNER JOIN (SELECT \"SAL\", AVG(\"COMM\") AS \"EXPR2\" FROM (SELECT \"SAL\", \"COMM\" FROM \"EMP\" GROUP BY \"SAL\", \"COMM\") AS \"t4\" GROUP BY \"SAL\") AS \"t5\" ON \"t2\".\"SAL\" IS NOT DISTINCT FROM \"t5\".\"SAL\" INNER JOIN (SELECT \"SAL\", SUM(\"SAL\") AS \"EXPR3\" FROM (SELECT \"SAL\" FROM \"EMP\" GROUP BY \"SAL\") AS \"t8\" GROUP BY \"SAL\") AS \"t9\" ON \"t2\".\"SAL\" IS NOT DISTINCT FROM \"t9\".\"SAL\"",
    "rewritten_query": "SELECT \"t2\".\"SAL\", \"t2\".\"EXPR1\", \"t5\".\"EXPR2\", \"t9\".\"EXPR3\" FROM (SELECT \"SAL\", SUM(\"COMM\") AS \"EXPR1\" FROM \"EMP\" GROUP BY \"SAL\") AS \"t2\" INNER JOIN (SELECT \"SAL\", AVG(\"COMM\") AS \"EXPR2\" FROM (SELECT \"SAL\", \"COMM\" FROM \"EMP\" GROUP BY \"SAL\", \"COMM\") AS \"t4\" GROUP BY \"SAL\") AS \"t5\" ON \"t2\".\"SAL\" IS NOT DISTINCT FROM \"t5\".\"SAL\" INNER JOIN (SELECT \"SAL\", SUM(\"SAL\") AS \"EXPR3\" FROM (SELECT \"SAL\" FROM \"EMP\" GROUP BY \"SAL\") AS \"t8\" GROUP BY \"SAL\") AS \"t9\" ON \"t2\".\"SAL\" IS NOT DISTINCT FROM \"t9\".\"SAL\"",
    "original_execution_time": 7.928715785344441,
    "rewrite_execution_time": 8.021686792373657,
    "speed_up": -0.011725859464033862,
    "times_up": 0.9884100427459216
  },
  {
    "id": 50,
    "equivalence": true,
    "original_query": "SELECT * FROM \"EMP\" LEFT JOIN (SELECT * FROM \"DEPT\") AS \"t\" ON \"EMP\".\"DEPTNO\" = \"t\".\"DEPTNO\" ORDER BY \"EMP\".\"SAL\" FETCH NEXT 10 ROWS ONLY",
    "rewritten_query": "SELECT * FROM \"EMP\" LEFT JOIN (SELECT * FROM \"DEPT\") AS \"t\" ON \"EMP\".\"DEPTNO\" = \"t\".\"DEPTNO\" ORDER BY \"EMP\".\"SAL\" FETCH NEXT 10 ROWS ONLY",
    "original_execution_time": 8.499905029932657,
    "rewrite_execution_time": 8.062923987706503,
    "speed_up": 0.051410108782076185,
    "times_up": 1.0541963489786605
  },
  {
    "id": 7,
    "equivalence": true,
    "original_query": "SELECT sal, SUM(comm), MIN(comm), SUM(DISTINCT sal) FROM emp GROUP BY sal;",
    "rewritten_query": "SELECT sal, SUM(comm), MIN(comm), sal FROM emp GROUP BY sal;",
    "original_execution_time": 16.22818398475647,
    "rewrite_execution_time": 1.735569715499878,
    "speed_up": 0.8930521297312046,
    "times_up": 9.350349824514215
  },
  {
    "id": 13,
    "equivalence": true,
    "original_query": "select * from emp e1  where e1.empno > SOME (select deptno from dept);",
    "rewritten_query": "SELECT * FROM emp e1 WHERE e1.empno > (SELECT MIN(deptno) FROM dept);",
    "original_execution_time": 91.00969958305359,
    "rewrite_execution_time": 20.07544493675232,
    "speed_up": 0.779414226959052,
    "times_up": 4.5333839359366435
  },
  {
    "id": 30,
    "equivalence": true,
    "original_query": "select e.mgr, d.mgr from emp as e full outer join emp as d on e.mgr = d.mgr group by d.mgr, e.mgr;",
    "rewritten_query": "SELECT e.mgr, d.mgr\nFROM (SELECT DISTINCT mgr FROM emp) e\nFULL OUTER JOIN (SELECT DISTINCT mgr FROM emp) d ON e.mgr = d.mgr;",
    "original_execution_time": 300,
    "rewrite_execution_time": 26.007601022720337,
    "speed_up": 0.9133079965909322,
    "times_up": 11.53508928939347
  },
  {
    "id": 31,
    "equivalence": true,
    "original_query": "select dname, ddeptno, c from              (select name dname, deptno ddeptno, count(*) as c              from dept group by grouping sets ((name,deptno),(name))) t               where dname = 'Charlie';",
    "rewritten_query": "SELECT dname, ddeptno, c \nFROM (\n    SELECT name AS dname, deptno AS ddeptno, COUNT(*) AS c \n    FROM dept \n    WHERE name = 'Charlie' \n    GROUP BY GROUPING SETS ((name, deptno), (name))\n) t;",
    "original_execution_time": 0.4316749572753906,
    "rewrite_execution_time": 0.017974138259887695,
    "speed_up": 0.9583618693719568,
    "times_up": 24.016448022921114
  },
  {
    "id": 35,
    "equivalence": true,
    "original_query": "select distinct d.deptno from emp e right outer join dept d on e.deptno = d.deptno;",
    "rewritten_query": "select deptno from dept;",
    "original_execution_time": 16.23289465904236,
    "rewrite_execution_time": 0.04691886901855469,
    "speed_up": 0.9971096424880439,
    "times_up": 345.9779615025001
  },
  {
    "id": 43,
    "equivalence": true,
    "original_query": "with e2 as (   select empno, case when true then deptno else null end as deptno   from emp) select empno,   deptno in (select deptno from e2 where empno < 20) as d from e2;",
    "rewritten_query": "/*+ Rows(emp emp #1) */\nSELECT empno, deptno IN (SELECT deptno FROM emp WHERE empno < 20) AS d\nFROM emp;",
    "original_execution_time": 300,
    "rewrite_execution_time": 7.6298441886901855,
    "speed_up": 0.9745671860376994,
    "times_up": 39.319282619780594
  },
  {
    "id": 18,
    "equivalence": true,
    "original_query": "select empno, sum(sal), min(sal), max(sal),  bit_and(distinct sal), bit_or(sal), count(distinct sal),  grouping(deptno) from emp group by empno, deptno;",
    "rewritten_query": "select empno, sum(sal), min(sal), max(sal),  bit_and(distinct sal), bit_or(sal), count(distinct sal),  grouping(deptno) from emp group by empno, deptno;",
    "original_execution_time": 43.35750102996826,
    "rewrite_execution_time": 42.31504487991333,
    "speed_up": 0.024043271067084714,
    "times_up": 1.0246355912657859
  },
  {
    "id": 20,
    "equivalence": true,
    "original_query": "select empno, count(mgr) from emp group by empno, deptno;",
    "rewritten_query": "select empno, count(mgr) from emp group by empno, deptno;",
    "original_execution_time": 12.155855417251587,
    "rewrite_execution_time": 14.06605577468872,
    "speed_up": -0.15714240519233044,
    "times_up": 0.8641978683978732
  },
  {
    "id": 21,
    "equivalence": true,
    "original_query": "select * from emp where empno > ANY (  select deptno from dept where emp.job = dept.name);",
    "rewritten_query": "select * from emp where empno > ANY (  select deptno from dept where emp.job = dept.name);",
    "original_execution_time": 300,
    "rewrite_execution_time": 300,
    "speed_up": 0.0,
    "times_up": 1.0
  },
  {
    "id": 27,
    "equivalence": true,
    "original_query": "select deptno c, min(y), max(z) z, sum(r), sum(m) n, sum(x) sal from (    select deptno, ename, sum(sal) x, max(sal) z,       min(sal) y, count(hiredate) m, count(mgr) r    from emp group by deptno, ename) t group by deptno;",
    "rewritten_query": "select deptno c, min(y), max(z) z, sum(r), sum(m) n, sum(x) sal from (    select deptno, ename, sum(sal) x, max(sal) z,       min(sal) y, count(hiredate) m, count(mgr) r    from emp group by deptno, ename) t group by deptno;",
    "original_execution_time": 31.83673334121704,
    "rewrite_execution_time": 32.44030475616455,
    "speed_up": -0.018958333710893113,
    "times_up": 0.9813943975100045
  },
  {
    "id": 29,
    "equivalence": true,
    "original_query": "select coalesce(sum(count_comm), 0) from (   select deptno, count(comm) as count_comm   from emp   group by deptno, mgr) t;",
    "rewritten_query": "SELECT COUNT(comm) FROM emp;",
    "original_execution_time": 33.235201597213745,
    "rewrite_execution_time": 1.1551392078399658,
    "speed_up": 0.9652435023009818,
    "times_up": 28.771598584521584
  }
]